lmc.vhd
library ieee; 

use ieee.std_logic_1164.all;
use ieee.numeric_std.all;

entity lmc is
    port(
        clk:         in  std_logic;
        rst:         in  std_logic;
        input:       in  signed(11 downto 0);
        output:      out signed(11 downto 0);
        input_warn:  out std_logic;
        output_warn: out std_logic;
        halt_warn:   out std_logic
    );
end entity;

architecture lmc of lmc is

    subtype word_t        is std_logic_vector(11 downto 0);
    subtype instruction_t is std_logic_vector(3 downto 0);
    
    type memory_t is array(255 downto 0) of word_t;
    
    signal ordinal_counter: natural := 0; -- index memory
    signal accumulator:     signed(11 downto 0);
    
    signal instruction_register: word_t;
    signal instruction:          instruction_t;
    signal address:              natural; -- index memory

    constant HLT: instruction_t := x"0"; -- halt (coffee break)
    constant ADD: instruction_t := x"1"; -- add 
    constant SUB: instruction_t := x"2";
    constant STA: instruction_t := x"3";
    constant NOP: instruction_t := x"4";
    constant LDA: instruction_t := x"5";
    constant BRA: instruction_t := x"6";
    constant BRZ: instruction_t := x"7";
    constant BRP: instruction_t := x"8";
    constant IO:  instruction_t := x"9"; -- 901 in, 902 out

    signal memory: memory_t := (
        0   => x"901",
        1   => x"1FF",
        2   => x"902",
        3   => x"901",
        4   => x"2FF",
        5   => x"902",
        6   => x"901",
        7   => x"3F0",
              
        8   => x"901",
        9   => x"400",
        10  => x"5F0",
        11  => x"902",
          
        12  => x"901",
        13  => x"70C",
        14  => x"5FE",
        15  => x"902",
        
        16  => x"901",
        17  => x"810",
        18  => x"5FD",
        19  => x"902",
        
        20  => x"600",		
            
        -- data
        253 => x"00A",
        254 => x"00B",
        255 => x"005",

        others	=> x"000"
   );

begin

    instruction_register <= memory(ordinal_counter);
    instruction          <= instruction_register(11 downto 8);
    address              <= to_integer(unsigned(instruction_register(7 downto 0)));
    
    -- output combinatory
    input_warn  <= '1' when instruction = IO and address = 1 else '0';
    output_warn <= '1' when instruction = IO and address = 2 else '0';
    halt_warn   <= '1' when instruction = HLT else '0';

    process (clk, rst) is
    begin

        if rst = '1' then
            ordinal_counter <= 0;
        elsif rising_edge(clk) then

            case instruction is
                when HLT => -- terminate the program (counter will not increase)
                    null;
                when ADD => 
                    accumulator <= accumulator + signed(memory(address));
                    ordinal_counter <= ordinal_counter + 1;
                when SUB => 
                    accumulator <= accumulator - signed(memory(address));
                    ordinal_counter <= ordinal_counter + 1;
                when LDA => 
                    accumulator <= signed(memory(address));
                    ordinal_counter <= ordinal_counter + 1;
                when NOP =>
                    ordinal_counter <= ordinal_counter + 1;
                when STA => 
                    memory(address) <= std_logic_vector(accumulator); 
                    ordinal_counter <= ordinal_counter + 1;
                when BRA => 
                    ordinal_counter <= address;             
                when BRZ =>
                    if accumulator = 0 then
                        ordinal_counter <= address;
                    else
                        ordinal_counter <= ordinal_counter + 1;
                    end if;
                when BRP =>
                    if accumulator >= 0 then
                        ordinal_counter <= address;
                    else
                        ordinal_counter <= ordinal_counter + 1;
                    end if;
                when IO  =>
                    case address is
                        when 1 => -- 901
                            accumulator <= input;
                        when 2 => -- 902
                            output <= accumulator;
                        when others =>
                            assert FALSE report "Illegal instruction" severity ERROR;
                    end case;
                    ordinal_counter <= ordinal_counter + 1;
                when others =>
                    assert FALSE report "Illegal instruction" severity ERROR;
            end case;
        end if;
    end process;
end architecture;

testbed.vcd
$date
  Thu Feb 27 11:27:43 2014
$end
$version
  GHDL v0
$end
$timescale
  1 fs
$end
$var reg 1 ! rst $end
$var reg 12 " input[11:0] $end
$var reg 12 # output[11:0] $end
$var reg 1 $ input_warn $end
$var reg 1 % output_warn $end
$var reg 1 & halt_warn $end
$var reg 1 ' clk $end
$scope module lmc $end
$var reg 1 ( clk $end
$var reg 1 ) rst $end
$var reg 12 * input[11:0] $end
$var reg 12 + output[11:0] $end
$var reg 1 , input_warn $end
$var reg 1 - output_warn $end
$var reg 1 . halt_warn $end
$var integer 32 / ordinal_counter $end
$var reg 12 0 accumulator[11:0] $end
$var reg 12 1 instruction_register[11:0] $end
$var reg 4 2 instruction[3:0] $end
$var integer 32 3 address $end
$comment memory is not handled $end
$upscope $end
$enddefinitions $end
#0
U!
bUUUUUUUUUUUU "
bUUUUUUUUUUUU #
1$
0%
0&
1'
1(
U)
bUUUUUUUUUUUU *
bUUUUUUUUUUUU +
1,
0-
0.
b0 /
bUUUUUUUUUUUU 0
b100100000001 1
b1001 2
b1 3
#1000000000000000
0'
0(
#2000000000000000
0$
1'
1(
0,
b1 /
b000111111111 1
b0001 2
b11111111 3
#3000000000000000
0'
0(
#4000000000000000
1%
1'
1(
1-
b10 /
bXXXXXXXXXXXX 0
b100100000010 1
b1001 2
b10 3
#5000000000000000
0'
0(
#6000000000000000
bXXXXXXXXXXXX #
1$
0%
1'
1(
bXXXXXXXXXXXX +
1,
0-
b11 /
b100100000001 1
b1 3
#7000000000000000
0'
0(
#8000000000000000
0$
1'
1(
0,
b100 /
bUUUUUUUUUUUU 0
b001011111111 1
b0010 2
b11111111 3
#9000000000000000
0'
0(
#10000000000000000
1%
1'
1(
1-
b101 /
bXXXXXXXXXXXX 0
b100100000010 1
b1001 2
b10 3
#11000000000000000
0'
0(
#12000000000000000
1$
0%
1'
1(
1,
0-
b110 /
b100100000001 1
b1 3
#13000000000000000
0'
0(
#14000000000000000
0$
1'
1(
0,
b111 /
bUUUUUUUUUUUU 0
b001111110000 1
b0011 2
b11110000 3
#15000000000000000
0'
0(
#16000000000000000
1$
1'
1(
1,
b1000 /
b100100000001 1
b1001 2
b1 3
#17000000000000000
0'
0(
#18000000000000000
0$
1'
1(
0,
b1001 /
b010000000000 1
b0100 2
b0 3
#19000000000000000
0'
0(
#20000000000000000
1'
1(
b1010 /
b010111110000 1
b0101 2
b11110000 3
#21000000000000000
0'
0(
#22000000000000000
1%
1'
1(
1-
b1011 /
b100100000010 1
b1001 2
b10 3
#23000000000000000
0'
0(
#24000000000000000
bUUUUUUUUUUUU #
1$
0%
1'
1(
bUUUUUUUUUUUU +
1,
0-
b1100 /
b100100000001 1
b1 3
#25000000000000000
0'
0(
#26000000000000000
0$
1'
1(
0,
b1101 /
b011100001100 1
b0111 2
b1100 3
#27000000000000000
0'
0(
#28000000000000000
1'
1(
b1110 /
b010111111110 1
b0101 2
b11111110 3
#29000000000000000
0'
0(
#30000000000000000
1%
1'
1(
1-
b1111 /
b000000001011 0
b100100000010 1
b1001 2
b10 3
#31000000000000000
0'
0(
#32000000000000000
b000000001011 #
1$
0%
1'
1(
b000000001011 +
1,
0-
b10000 /
b100100000001 1
b1 3
#33000000000000000
0'
0(
#34000000000000000
0$
1'
1(
0,
b10001 /
bUUUUUUUUUUUU 0
b100000010000 1
b1000 2
b10000 3
#35000000000000000
0'
0(
#36000000000000000
1'
1(
b10010 /
b010111111101 1
b0101 2
b11111101 3
#37000000000000000
0'
0(
#38000000000000000
1%
1'
1(
1-
b10011 /
b000000001010 0
b100100000010 1
b1001 2
b10 3
#39000000000000000
0'
0(
#40000000000000000
b000000001010 #
0%
1'
1(
b000000001010 +
0-
b10100 /
b011000000000 1
b0110 2
b0 3
#41000000000000000
0'
0(
#42000000000000000
1$
1'
1(
1,
b0 /
b100100000001 1
b1001 2
b1 3
#43000000000000000
0'
0(
#44000000000000000
0$
1'
1(
0,
b1 /
bUUUUUUUUUUUU 0
b000111111111 1
b0001 2
b11111111 3
#45000000000000000
0'
0(
#46000000000000000
1%
1'
1(
1-
b10 /
bXXXXXXXXXXXX 0
b100100000010 1
b1001 2
b10 3
#47000000000000000
0'
0(
#48000000000000000
bXXXXXXXXXXXX #
1$
0%
1'
1(
bXXXXXXXXXXXX +
1,
0-
b11 /
b100100000001 1
b1 3
#49000000000000000
0'
0(
#50000000000000000
0$
1'
1(
0,
b100 /
bUUUUUUUUUUUU 0
b001011111111 1
b0010 2
b11111111 3
#51000000000000000
0'
0(
#52000000000000000
1%
1'
1(
1-
b101 /
bXXXXXXXXXXXX 0
b100100000010 1
b1001 2
b10 3
#53000000000000000
0'
0(
#54000000000000000
1$
0%
1'
1(
1,
0-
b110 /
b100100000001 1
b1 3
#55000000000000000
0'
0(
#56000000000000000
0$
1'
1(
0,
b111 /
bUUUUUUUUUUUU 0
b001111110000 1
b0011 2
b11110000 3
#57000000000000000
0'
0(
#58000000000000000
1$
1'
1(
1,
b1000 /
b100100000001 1
b1001 2
b1 3
#59000000000000000
0'
0(
#60000000000000000
0$
1'
1(
0,
b1001 /
b010000000000 1
b0100 2
b0 3
#61000000000000000
0'
0(
#62000000000000000
1'
1(
b1010 /
b010111110000 1
b0101 2
b11110000 3
#63000000000000000
0'
0(
#64000000000000000
1%
1'
1(
1-
b1011 /
b100100000010 1
b1001 2
b10 3
#65000000000000000
0'
0(
#66000000000000000
bUUUUUUUUUUUU #
1$
0%
1'
1(
bUUUUUUUUUUUU +
1,
0-
b1100 /
b100100000001 1
b1 3
#67000000000000000
0'
0(
#68000000000000000
0$
1'
1(
0,
b1101 /
b011100001100 1
b0111 2
b1100 3
#69000000000000000
0'
0(
#70000000000000000
1'
1(
b1110 /
b010111111110 1
b0101 2
b11111110 3
#71000000000000000
0'
0(
#72000000000000000
1%
1'
1(
1-
b1111 /
b000000001011 0
b100100000010 1
b1001 2
b10 3
#73000000000000000
0'
0(
#74000000000000000
b000000001011 #
1$
0%
1'
1(
b000000001011 +
1,
0-
b10000 /
b100100000001 1
b1 3
#75000000000000000
0'
0(
#76000000000000000
0$
1'
1(
0,
b10001 /
bUUUUUUUUUUUU 0
b100000010000 1
b1000 2
b10000 3
#77000000000000000
0'
0(
#78000000000000000
1'
1(
b10010 /
b010111111101 1
b0101 2
b11111101 3
#79000000000000000
0'
0(
#80000000000000000
1%
1'
1(
1-
b10011 /
b000000001010 0
b100100000010 1
b1001 2
b10 3
#81000000000000000
0'
0(
#82000000000000000
b000000001010 #
0%
1'
1(
b000000001010 +
0-
b10100 /
b011000000000 1
b0110 2
b0 3
#83000000000000000
0'
0(
#84000000000000000
1$
1'
1(
1,
b0 /
b100100000001 1
b1001 2
b1 3
#85000000000000000
0'
0(
#86000000000000000
0$
1'
1(
0,
b1 /
bUUUUUUUUUUUU 0
b000111111111 1
b0001 2
b11111111 3
#87000000000000000
0'
0(
#88000000000000000
1%
1'
1(
1-
b10 /
bXXXXXXXXXXXX 0
b100100000010 1
b1001 2
b10 3
#89000000000000000
0'
0(
#90000000000000000
bXXXXXXXXXXXX #
1$
0%
1'
1(
bXXXXXXXXXXXX +
1,
0-
b11 /
b100100000001 1
b1 3
#91000000000000000
0'
0(
#92000000000000000
0$
1'
1(
0,
b100 /
bUUUUUUUUUUUU 0
b001011111111 1
b0010 2
b11111111 3
#93000000000000000
0'
0(
#94000000000000000
1%
1'
1(
1-
b101 /
bXXXXXXXXXXXX 0
b100100000010 1
b1001 2
b10 3
#95000000000000000
0'
0(
#96000000000000000
1$
0%
1'
1(
1,
0-
b110 /
b100100000001 1
b1 3
#97000000000000000
0'
0(
#98000000000000000
0$
1'
1(
0,
b111 /
bUUUUUUUUUUUU 0
b001111110000 1
b0011 2
b11110000 3
#99000000000000000
0'
0(
#100000000000000000
1$
1'
1(
1,
b1000 /
b100100000001 1
b1001 2
b1 3
